ankit_db/__init__.py
ankit_db/deserialize.py
ankit_db/discover.py
ankit_db/dynamodb.py
ankit_db/sync.py
ankit_db/sync_strategies/__init__.py
ankit_db/sync_strategies/full_table.py
ankit_db/sync_strategies/log_based.py
ankit_db-1.4.4.dist-info/LICENSE
ankit_db-1.4.4.dist-info/METADATA
ankit_db-1.4.4.dist-info/WHEEL
ankit_db-1.4.4.dist-info/entry_points.txt
ankit_db-1.4.4.dist-info/top_level.txt
ankit_db-1.4.4.dist-info/RECORD
